nrel/routee/compass/__init__.py
nrel/routee/compass/compass_app.py
nrel/routee/compass/io/__init__.py
nrel/routee/compass/io/charging_station_ops.py
nrel/routee/compass/io/convert_results.py
nrel/routee/compass/io/generate_dataset.py
nrel/routee/compass/io/utils.py
nrel/routee/compass/plot/__init__.py
nrel/routee/compass/plot/plot_folium.py
nrel/routee/compass/plot/plot_utils.py
nrel/routee/compass/py.typed
nrel/routee/compass/resources/__init__.py
nrel/routee/compass/resources/downtown_denver_example/denver_metro.geojson
nrel/routee/compass/resources/downtown_denver_example/edges-compass.csv.gz
nrel/routee/compass/resources/downtown_denver_example/edges-complete.csv.gz
nrel/routee/compass/resources/downtown_denver_example/edges-geometries-enumerated.txt.gz
nrel/routee/compass/resources/downtown_denver_example/edges-grade-enumerated.txt.gz
nrel/routee/compass/resources/downtown_denver_example/edges-headings-enumerated.csv.gz
nrel/routee/compass/resources/downtown_denver_example/edges-mapping.csv.gz
nrel/routee/compass/resources/downtown_denver_example/edges-posted-speed-enumerated.txt.gz
nrel/routee/compass/resources/downtown_denver_example/edges-road-class-enumerated.txt.gz
nrel/routee/compass/resources/downtown_denver_example/edges-uuid-enumerated.txt.gz
nrel/routee/compass/resources/downtown_denver_example/models/2016_CHEVROLET_Volt_Charge_Depleting.bin
nrel/routee/compass/resources/downtown_denver_example/models/2016_CHEVROLET_Volt_Charge_Sustaining.bin
nrel/routee/compass/resources/downtown_denver_example/models/2016_TOYOTA_Camry_4cyl_2WD.bin
nrel/routee/compass/resources/downtown_denver_example/models/2017_CHEVROLET_Bolt.bin
nrel/routee/compass/resources/downtown_denver_example/models/__init__.py
nrel/routee/compass/resources/downtown_denver_example/models/download_links.json
nrel/routee/compass/resources/downtown_denver_example/osm_default_distance.toml
nrel/routee/compass/resources/downtown_denver_example/osm_default_energy.toml
nrel_routee_compass-0.16.0.dist-info/METADATA
nrel_routee_compass-0.16.0.dist-info/WHEEL
nrel_routee_compass-0.16.0.dist-info/licenses/LICENSE.md
nrel_routee_compass-0.16.0.dist-info/RECORD
