Metadata-Version: 2.4
Name: nrel_routee_compass
Version: 0.16.0
Classifier: Development Status :: 3 - Alpha
Classifier: Intended Audience :: Science/Research
Classifier: License :: Other/Proprietary License
Classifier: Operating System :: OS Independent
Classifier: Programming Language :: Python
Classifier: Topic :: Scientific/Engineering
Requires-Dist: tomlkit>=0.11.0,<1.0
Requires-Dist: pytest>=8.0,<9.0 ; extra == 'dev'
Requires-Dist: maturin>=1.0,<2.0 ; extra == 'dev'
Requires-Dist: jupyter-book>=1.0,<2.0 ; extra == 'dev'
Requires-Dist: ruff>=0.1.0,<1.0 ; extra == 'dev'
Requires-Dist: sphinx-book-theme>=1.0.0,<2.0 ; extra == 'dev'
Requires-Dist: mypy>=1.0.0,<2.0 ; extra == 'dev'
Requires-Dist: jupyterlab>=4.0.0,<5.0 ; extra == 'dev'
Requires-Dist: boxsdk>=3.0.0,<4.0 ; extra == 'dev'
Requires-Dist: types-requests>=2.28.0,<3.0 ; extra == 'dev'
Requires-Dist: osmnx>=2.0.5,<3.0 ; extra == 'osm'
Requires-Dist: rio-vrt>=0.3.1,<1.0 ; extra == 'osm'
Requires-Dist: mapclassify>=2.8.1,<3.0 ; extra == 'osm'
Requires-Dist: requests>=2.28.0,<3.0 ; extra == 'osm'
Requires-Dist: geopandas>=1.1.1,<2.0 ; extra == 'osm'
Requires-Dist: shapely>=2.0.0,<3.0 ; extra == 'osm'
Requires-Dist: networkx>=3.0,<4.0 ; extra == 'osm'
Requires-Dist: folium>=0.14.0,<1.0 ; extra == 'osm'
Requires-Dist: pandas>=2.0.0,<3.0 ; extra == 'osm'
Requires-Dist: rasterio>=1.3.0,<2.0 ; extra == 'osm'
Requires-Dist: matplotlib>=3.7.0,<4.0 ; extra == 'osm'
Requires-Dist: numpy>=1.26,<3.0 ; extra == 'osm'
Requires-Dist: seaborn>=0.12.0,<1.0 ; extra == 'osm'
Requires-Dist: nrel-routee-compass[osm] ; extra == 'all'
Requires-Dist: nrel-routee-compass[dev] ; extra == 'all'
Provides-Extra: dev
Provides-Extra: osm
Provides-Extra: all
License-File: LICENSE.md
Summary: An eco-routing tool build upon RouteE-Powertrain
Keywords: eco routing
Home-Page: https://nrel.github.io/routee-compass
Author: National Renewable Energy Laboratory
License: BSD 3-Clause License Copyright (c) 2023, Alliance for Sustainable Energy, LLC
Requires-Python: >=3.10, <3.14
Project-URL: Homepage, https://github.com/NREL/routee-compass
Project-URL: Documentation, https://nrel.github.io/routee-compass
